gaelib/__init__.py
gaelib/defaults.py
gaelib/env.py
gaelib/filters.py
gaelib/urls.py
gaelib/auth/__init__.py
gaelib/auth/auth.py
gaelib/auth/decorators.py
gaelib/auth/models.py
gaelib/auth/twilio_client.py
gaelib/auth/verify.py
gaelib/auth/views.py
gaelib/clientlogger/__init__.py
gaelib/clientlogger/logging.py
gaelib/cron/__init__.py
gaelib/cron/constants.py
gaelib/cron/decorators.py
gaelib/dashboard/__init__.py
gaelib/dashboard/views.py
gaelib/dashboard/templates/base.html
gaelib/dashboard/templates/failure.html
gaelib/dashboard/templates/logged_in_base.html
gaelib/dashboard/templates/login.html
gaelib/dashboard/templates/logout.html
gaelib/dashboard/templates/notifications.html
gaelib/dashboard/templates/public_base.html
gaelib/dashboard/templates/user_failure.html
gaelib/db/__init__.py
gaelib/db/constants.py
gaelib/db/helpers.py
gaelib/db/model.py
gaelib/db/properties.py
gaelib/db/query.py
gaelib/storage/__init__.py
gaelib/storage/helpers.py
gaelib/tasks/__init__.py
gaelib/tasks/decorators.py
gaelib/tasks/notification_task.py
gaelib/tests/__init__.py
gaelib/tests/base.py
gaelib/tests/auth/__init__.py
gaelib/tests/auth/base.py
gaelib/tests/auth/test_auth.py
gaelib/tests/auth/test_decorators.py
gaelib/tests/auth/test_verify.py
gaelib/tests/auth/test_views.py
gaelib/tests/cron/__init__.py
gaelib/tests/cron/test_decorators.py
gaelib/tests/db/__init__.py
gaelib/tests/db/model.py
gaelib/tests/db/test_helpers.py
gaelib/tests/db/test_model.py
gaelib/tests/storage/__init__.py
gaelib/tests/storage/test_helpers.py
gaelib/tests/tasks/__init__.py
gaelib/tests/tasks/base.py
gaelib/tests/tasks/test_notification_task.py
gaelib/utils/__init__.py
gaelib/utils/notifications.py
gaelib/utils/task.py
gaelib/utils/web.py
gaelib/view/__init__.py
gaelib/view/base_view.py
gaelib-0.1.8.dist-info/LICENSE.txt
gaelib-0.1.8.dist-info/METADATA
gaelib-0.1.8.dist-info/WHEEL
gaelib-0.1.8.dist-info/top_level.txt
gaelib-0.1.8.dist-info/RECORD
