Metadata-Version: 2.1
Name: gaelib
Version: 0.1.8
Summary: Google App Engine Library
Author: Shantanu Mallik
License: gpl-3.0
License-File: LICENSE.txt
Requires-Dist: wheel (==0.36.2)
Requires-Dist: google-cloud-speech (==2.4.0)
Requires-Dist: google-cloud-core (==1.3.0)
Requires-Dist: grpcio (==1.38.0)
Requires-Dist: google-auth (==1.35.0)
Requires-Dist: google-cloud-datastore (==1.15.3)
Requires-Dist: requests (==2.25.1)
Requires-Dist: google-cloud-logging (==1.15.1)
Requires-Dist: google-cloud-storage (==1.30.0)
Requires-Dist: google-cloud-speech (==1.3.2)
Requires-Dist: google-api-core (==1.32.0)
Requires-Dist: google-api-python-client (==1.9.1)
Requires-Dist: py-dateutil (==2.2)
Requires-Dist: pyjwt (==1.7.1)
Requires-Dist: hyper
Requires-Dist: google-cloud-tasks (==2.0.0)
Requires-Dist: googleapis-common-protos (==1.53.0)
Requires-Dist: firebase-admin (==4.3.0)
Requires-Dist: python-jose (==3.3.0)
Requires-Dist: nose (==1.3.7)
Requires-Dist: mock (==2.0.0)
Requires-Dist: google-cloud (==0.34.0)
Requires-Dist: Flask (==2.0.1)
Requires-Dist: Flask-Cors (==3.0.9)
Requires-Dist: gunicorn (==20.1.0)
Requires-Dist: Jinja2 (==3.0.1)
Requires-Dist: six (==1.15.0)
Requires-Dist: Werkzeug (==2.0.1)
Requires-Dist: twilio (==6.59.1)
Requires-Dist: certifi (==2021.5.30)
Requires-Dist: chardet (==4.0.0)
Requires-Dist: click (==8.0.1)
Requires-Dist: cachetools (==4.2.2)
Requires-Dist: constants (==0.6.0)
Requires-Dist: protobuf (==3.19.4)
